README.rst
setup.py
hawkweed/__init__.py
hawkweed.egg-info/PKG-INFO
hawkweed.egg-info/SOURCES.txt
hawkweed.egg-info/dependency_links.txt
hawkweed.egg-info/top_level.txt
hawkweed/classes/__init__.py
hawkweed/classes/collection.py
hawkweed/classes/dict_cls.py
hawkweed/classes/future.py
hawkweed/classes/iterable.py
hawkweed/classes/list_cls.py
hawkweed/classes/repr.py
hawkweed/classes/set_cls.py
hawkweed/computed/__init__.py
hawkweed/functional/__init__.py
hawkweed/functional/list_prims.py
hawkweed/functional/logical.py
hawkweed/functional/mathematical.py
hawkweed/functional/primitives.py
hawkweed/monads/__init__.py
hawkweed/monads/continuation.py
hawkweed/monads/either.py
hawkweed/monads/identity.py
hawkweed/monads/io.py
hawkweed/monads/listm.py
hawkweed/monads/maybe.py
hawkweed/monads/monad.py
tests/__init__.py
tests/test_collection.py
tests/test_continuation.py
tests/test_dict.py
tests/test_either.py
tests/test_future.py
tests/test_identity.py
tests/test_io.py
tests/test_iterable.py
tests/test_list.py
tests/test_list_prims.py
tests/test_listm.py
tests/test_logical.py
tests/test_math.py
tests/test_mathematical.py
tests/test_maybe.py
tests/test_monad.py
tests/test_primitives.py
tests/test_repr.py
tests/test_set.py