Metadata-Version: 1.1
Name: hawkweed
Version: 0.1.5
Summary: Extending Python builtin types
Home-page: https://github.com/hellerve/hawkweed
Author: Veit Heller
Author-email: veit@veitheller.de
License: MIT License
Download-URL: https://github.com/hellerve/hawkweed/tarball/0.1.5
Platform: UNKNOWN
